Metadata-Version: 1.1
Name: Mgf
Version: 0.0.1
Summary: Heh!
Home-page: https://code.xueersi.com/space/47013434
Author: 123_python
Author-email: QQsped2020@Tom.com
License: MIT
Keywords: Deep Learning,Machine Learning,Neural Networks,Scientific computing,Differential equations,PDE solver
Platform: UNKNOWN
Classifier: License :: OSI Approved :: MIT License
Classifier: Programming Language :: Python
Classifier: Intended Audience :: Developers
Classifier: Operating System :: OS Independent
